{
  "schema": "hls.bandwidth_utilization_summary.v1",
  "source": "inferred_physical_axi_transactions",
  "total": {
    "transaction_count": 8,
    "logical_element_count": 2048,
    "useful_bytes": 8192,
    "transferred_bytes": 8192,
    "unused_bytes": 0,
    "read_transactions": 8,
    "write_transactions": 0,
    "bandwidth_utilization": 1.0
  },
  "ports": {
    "mem_0": {
      "transaction_count": 4,
      "logical_element_count": 1024,
      "useful_bytes": 4096,
      "transferred_bytes": 4096,
      "unused_bytes": 0,
      "read_transactions": 4,
      "write_transactions": 0,
      "bandwidth_utilization": 1.0
    },
    "mem_1": {
      "transaction_count": 4,
      "logical_element_count": 1024,
      "useful_bytes": 4096,
      "transferred_bytes": 4096,
      "unused_bytes": 0,
      "read_transactions": 4,
      "write_transactions": 0,
      "bandwidth_utilization": 1.0
    }
  }
}
